zypzctest/__init__.py
zypzctest/get_haha.py
zypzctest-0.0.2.dist-info/LICENSE.lic
zypzctest-0.0.2.dist-info/METADATA
zypzctest-0.0.2.dist-info/WHEEL
zypzctest-0.0.2.dist-info/top_level.txt
zypzctest-0.0.2.dist-info/RECORD
