Metadata-Version: 2.1
Name: zypzctest
Version: 0.0.2
Summary: This project is for testing. It doesn't have any function.
Home-page: https://gitee.com/always-on-the-road-pzc/220208
Author: PZC
Author-email: 2556616974@qq.com
License-File: LICENSE.lic
